{"metadata": {"dbt_schema_version": "https://schemas.getdbt.com/dbt/run-results/v6.json", "dbt_version": "1.10.13", "generated_at": "2025-09-30T12:34:48.601487Z", "invocation_id": "b84b7408-6ca7-42cd-92b1-e4e199e8b2de", "invocation_started_at": "2025-09-30T12:34:48.066757Z", "env": {}}, "results": [{"status": "success", "timing": [{"name": "compile", "started_at": "2025-09-30T12:34:48.583563Z", "completed_at": "2025-09-30T12:34:48.585252Z"}, {"name": "execute", "started_at": "2025-09-30T12:34:48.585790Z", "completed_at": "2025-09-30T12:34:48.585802Z"}], "thread_id": "Thread-2 (worker)", "execution_time": 0.007824897766113281, "adapter_response": {}, "message": null, "failures": null, "unique_id": "model.dbt_pfl_statistics.stg_example", "compiled": true, "compiled_code": "select 1 as example_col", "relation_name": "\"plt\".\"analytics_staging\".\"stg_example\"", "batch_results": null}, {"status": "success", "timing": [{"name": "compile", "started_at": "2025-09-30T12:34:48.578755Z", "completed_at": "2025-09-30T12:34:48.585549Z"}, {"name": "execute", "started_at": "2025-09-30T12:34:48.586392Z", "completed_at": "2025-09-30T12:34:48.586400Z"}], "thread_id": "Thread-1 (worker)", "execution_time": 0.008632898330688477, "adapter_response": {}, "message": null, "failures": null, "unique_id": "model.dbt_pfl_statistics.mart_example", "compiled": true, "compiled_code": "-- dbt/models/marts/example_mart.sql\nselect 1 as mart_check", "relation_name": "\"plt\".\"analytics_analytics\".\"mart_example\"", "batch_results": null}, {"status": "success", "timing": [{"name": "compile", "started_at": "2025-09-30T12:34:48.588072Z", "completed_at": "2025-09-30T12:34:48.599093Z"}, {"name": "execute", "started_at": "2025-09-30T12:34:48.599603Z", "completed_at": "2025-09-30T12:34:48.599610Z"}], "thread_id": "Thread-4 (worker)", "execution_time": 0.012323141098022461, "adapter_response": {}, "message": null, "failures": null, "unique_id": "test.dbt_pfl_statistics.not_null_stg_example_example_col.f4d5474a09", "compiled": true, "compiled_code": "\n    \n    \n\n\n\nselect example_col\nfrom \"plt\".\"analytics_staging\".\"stg_example\"\nwhere example_col is null\n\n\n", "relation_name": null, "batch_results": null}, {"status": "success", "timing": [{"name": "compile", "started_at": "2025-09-30T12:34:48.596445Z", "completed_at": "2025-09-30T12:34:48.599371Z"}, {"name": "execute", "started_at": "2025-09-30T12:34:48.600021Z", "completed_at": "2025-09-30T12:34:48.600025Z"}], "thread_id": "Thread-2 (worker)", "execution_time": 0.00416874885559082, "adapter_response": {}, "message": null, "failures": null, "unique_id": "test.dbt_pfl_statistics.not_null_mart_example_mart_check.354e307b66", "compiled": true, "compiled_code": "\n    \n    \n\n\n\nselect mart_check\nfrom \"plt\".\"analytics_analytics\".\"mart_example\"\nwhere mart_check is null\n\n\n", "relation_name": null, "batch_results": null}], "elapsed_time": 0.0830540657043457, "args": {"introspect": true, "inject_ephemeral_ctes": true, "profiles_dir": "/Users/mohammed/.dbt", "static_parser": true, "require_generic_test_arguments_property": true, "show_resource_report": false, "state_modified_compare_more_unrendered_values": false, "require_yaml_configuration_for_mf_time_spines": false, "require_nested_cumulative_type_params": false, "partial_parse": true, "validate_macro_args": false, "log_level_file": "debug", "partial_parse_file_diff": true, "quiet": false, "send_anonymous_usage_stats": true, "strict_mode": false, "upload_to_artifacts_ingest_api": false, "warn_error_options": {"error": [], "warn": [], "silence": []}, "macro_debugging": false, "output": "text", "printer_width": 80, "use_colors": true, "populate_cache": true, "select": [], "log_format_file": "debug", "use_colors_file": true, "use_fast_test_edges": false, "invocation_command": "dbt compile", "defer": false, "write_json": true, "empty": false, "log_path": "/Users/mohammed/repos/GreatLockIn2025/dbt_projects/dbt_football_project/DBT_PFL_Statistics/logs", "indirect_selection": "eager", "skip_nodes_if_on_run_start_fails": false, "vars": {}, "require_all_warnings_handled_by_warn_error": false, "source_freshness_run_project_hooks": true, "print": true, "require_batched_execution_for_custom_microbatch_strategy": false, "show_all_deprecations": false, "log_file_max_bytes": 10485760, "state_modified_compare_vars": false, "version_check": true, "exclude": [], "log_level": "info", "favor_state": false, "require_explicit_package_overrides_for_builtin_materializations": true, "log_format": "default", "cache_selected_only": false, "require_resource_names_without_spaces": true, "which": "compile", "project_dir": "/Users/mohammed/repos/GreatLockIn2025/dbt_projects/dbt_football_project/DBT_PFL_Statistics"}}